reloading/__init__.py
reloading/reloading.py
reloading/test_reloading.py
reloading-1.1.1.dist-info/LICENSE.txt
reloading-1.1.1.dist-info/METADATA
reloading-1.1.1.dist-info/WHEEL
reloading-1.1.1.dist-info/top_level.txt
reloading-1.1.1.dist-info/RECORD
