Metadata-Version: 2.1
Name: reloading
Version: 1.1.1
Summary: Reloads source code of a running program without losing state
Home-page: https://github.com/julvo/reloading
Author: Julian Vossen
Author-email: pypi@julianvossen.de
License: MIT
Download-URL: https://github.com/julvo/reloading/archive/v1.1.1.tar.gz
Keywords: reload,reloading,refresh,loop,decorator
Platform: UNKNOWN
Classifier: Development Status :: 3 - Alpha
Classifier: Intended Audience :: Developers
Classifier: Topic :: Utilities
Classifier: License :: OSI Approved :: MIT License
Classifier: Programming Language :: Python :: 3
Classifier: Programming Language :: Python :: 3.4
Classifier: Programming Language :: Python :: 3.5
Classifier: Programming Language :: Python :: 3.6
Classifier: Programming Language :: Python :: 3.7
Classifier: Programming Language :: Python :: 3.8
Classifier: Programming Language :: Python :: 3.9
License-File: LICENSE.txt
